{
  // verbose
  "simulation": false,
  "print_timer": false,

  // algorithmic-level knobs
  "integration_method": "PrinceDormand", // "PrinceDormand", "RK4", //, Fehlberg
  "use_OOS": false, // update with Out-Of-State features
  "use_depth_opt": true,  // depth optimization
  "use_MH_gating": true,
  "use_1pt_RANSAC": false,  
  "use_compression": true,  // measurement compression
  "compression_trigger_ratio": 1.5,

  "PrinceDormand": {
    "control_stepsize": false,
    "tolerance": 1e-15,
    "attempts": 12,
    "min_scale_factor": 0.125,
    "max_scale_factor": 4.0,
    "stepsize": 0.002
  },

  "RK4": {
    "stepsize": 0.002
  },

  // memory
  "max_features": 256,
  "max_groups": 256,  // max groups should increase as allowed group lifetime increases

  "gravity": [0, 0, -9.8],
  "timing": false,

  // Initial State
  "X" : {
    "W"   : [0, 0, 0],
    "T"   : [0, 0, 0],
    "V"   : [0, 0, 0],
    "bg"  : [0, 0, 0],
    "ba"  : [0, 0, 0],
    "Wbc" : [[1, 0, 0],
             [0, 1, 0],
             [0, 0, 1]],
    "Tbc": [0, 0, 0],
    "Wg"  : [0, 0]
  },

  "P" : {
    "W"   : 0.001,
    "T"   : 0.01,
    "V"   : 0.5,
    "bg"  : 0.000,
    "ba"  : 0.00,
    "Wbc" : 0.00001,
    "Tbc" : 0.0001,
    "Wg"  : 0.01
  },

  "Qmodel" : {
    "W"   : 0.000,
    "T"   : 0.0,
    "V"   : 0.0,
    "wb"  : 0.0000,
    "ab"  : 0.000,
    "Wbc" : 0.000,
    "Tbc" : 0.0,
    "Wg"  : 0.000
  },

  // // exact densities provided by TUM-VI dataset
  // // https://vision.in.tum.de/data/datasets/visual-inertial-dataset
  "Qimu": {
    "gyro": 8.0e-5,
    "gyro_bias": 2.2e-6,
    "accel":1.4e-3,
    "accel_bias": 8.6e-5
  },

  // initial std on feature state
  "initial_z": 5.5, // meter
  "initial_std_x": 0.5, // pixel
  "initial_std_y": 0.5, // pixel
  "initial_std_z": 2.0,  // meter

  // std of visuale measurement, in pixels
  "visual_meas_std":  1.5,
  "subfilter_visual_meas_std":  1.5,
  "max_depth": 10.0,
  "min_depth": 0.05,
  "max_depth_init_steps": 5,

  "use_depth_opt": true,
  "depth_opt_iters": 5,
  "depth_opt_eps": 0.001,
  "depth_opt_damping": 1e-3,

  "feature_P0_damping": 10.0,
  "inn_thresh": 64,
  "MH_thresh": 8.991,

  "imu_calib": {
    "Cas": [1, 1, 1],
    "Car": [[1, 0, 0], 
            [0, 1, 0], 
            [0, 0, 1]],
    "Cgs": [1, 1, 1],
    "Cgr": [[1, 0, 0], 
            [0, 1, 0], 
            [0, 0, 1]]
  },
  "imu_init_counter": 5,

  "camera_cfg": {
    "model": "pinhole",
    "rows": 240, 
    "cols": 320,
    "fx": 277.12812921,
    "fy": 289.70562748,
    "cx": 160,
    "cy": 120,
    "comment": "pinhole"
  },

  "tracker_cfg": {
    "use_prediction": true,
    "mask_size": 15,
    "num_features_min": 60,
    "num_features_max": 90,
    "normalize": false,

    "OpticalFlow": {
      "win_size": 7,
      "max_level": 5,
      "max_iter": 15,
      "eps": 1e-4,
      "threshold": 20
    },

    // somehow, only BRISK and FAST work well with the generic FeatureDetector interface (Version 2.4.9)
    "DetectorType": "FAST",

    "FAST": {
      "threshold": 20,
      "nonmaxSuppression": true
    },

    "GridAdapter": {
      "grid_rows": 4,
      "grid_cols": 4
    }
  } 

}
